pycuGMRES/__init__.py
pycuGMRES/CUDA C ++ sources/Fast_matvec.cuh
pycuGMRES/CUDA C ++ sources/GMRES.cu
pycuGMRES/CUDA C ++ sources/GMRES.cuh
pycuGMRES/CUDA C ++ sources/GMRES_kernels.cuh
pycuGMRES/CUDA C ++ sources/GMRES_old.cuh
pycuGMRES/CUDA C ++ sources/GMRES_old_kernels.cuh
pycuGMRES/CUDA C ++ sources/GMRES_rmk.cuh
pycuGMRES/CUDA C ++ sources/TestGMRES.cu
pycuGMRES/CUDA C ++ sources/TestUpdGMRES.cuh
pycuGMRES/CUDA C ++ sources/pycuFunctions.cuh
pycuGMRES/CUDA C ++ sources/saveGPU.cuh
pycuGMRES/Shared object generating/compile_cpp.sh
pycuGMRES-1.1.4.6.9.dist-info/LICENSE.md
pycuGMRES-1.1.4.6.9.dist-info/METADATA
pycuGMRES-1.1.4.6.9.dist-info/WHEEL
pycuGMRES-1.1.4.6.9.dist-info/top_level.txt
pycuGMRES-1.1.4.6.9.dist-info/RECORD
