Metadata-Version: 2.1
Name: pycuGMRES
Version: 1.1.4.6.9
Summary: Fast CUDA C++ GMRES implementation for Toeplitz-like (Toeplitz, Hankel, Circulant) matrices and mixed (combinations of Diagonal ones and Toeplitz-like ones) matrices.
Home-page: https://github.com/archilless/pycuGMRES
Author: Iurii Borisovich Minin
Author-email: iurii.minin@skoltech.ru
License: MIT
Platform: UNKNOWN
Classifier: Programming Language :: Python :: 3
Classifier: Programming Language :: Python :: 3.4
Classifier: Programming Language :: Python :: 3.5
Classifier: Programming Language :: Python :: 3.6
Classifier: Programming Language :: Python :: 3.7
Classifier: Programming Language :: Python :: 3.8
Classifier: License :: OSI Approved :: MIT License
Classifier: Operating System :: OS Independent
